<profile>

<ReportVersion>
<Version>2020.2</Version>
</ReportVersion>

<UserAssignments>
<unit>ns</unit>
<ProductFamily>zynquplus</ProductFamily>
<Part>xczu3eg-sbva484-1-i</Part>
<TopModelName>hash_search</TopModelName>
<TargetClockPeriod>6.67</TargetClockPeriod>
<ClockUncertainty>1.80</ClockUncertainty>
<FlowTarget>vitis</FlowTarget>
</UserAssignments>

<PerformanceEstimates>
<PipelineType>none</PipelineType>
<SummaryOfTimingAnalysis>
<unit>ns</unit>
<EstimatedClockPeriod>2.653</EstimatedClockPeriod>
</SummaryOfTimingAnalysis>
<SummaryOfOverallLatency>
<unit>clock cycles</unit>
<Best-caseLatency>32</Best-caseLatency>
<Average-caseLatency>undef</Average-caseLatency>
<Worst-caseLatency>917617</Worst-caseLatency>
<Best-caseRealTimeLatency>0.213 us</Best-caseRealTimeLatency>
<Average-caseRealTimeLatency>undef</Average-caseRealTimeLatency>
<Worst-caseRealTimeLatency>6.121 ms</Worst-caseRealTimeLatency>
<Interval-min>32</Interval-min>
<Interval-max>917617</Interval-max>
</SummaryOfOverallLatency>
<SummaryOfLoopLatency>
<Loop1>
<TripCount>14</TripCount>
<Latency>14</Latency>
<AbsoluteTimeLatency>93</AbsoluteTimeLatency>
<IterationLatency>1</IterationLatency>
</Loop1>
<Loop2>
<TripCount>14</TripCount>
<Latency>14</Latency>
<AbsoluteTimeLatency>93</AbsoluteTimeLatency>
<IterationLatency>1</IterationLatency>
</Loop2>
<LOOP_HASH_SEARCH1>
<TripCount>
<range>
<min>1</min>
<max>14</max>
</range>
</TripCount>
<Latency>
<range>
<min>3</min>
<max>917578</max>
</range>
</Latency>
<AbsoluteTimeLatency>
<range>
<min>20</min>
<max>6120245</max>
</range>
</AbsoluteTimeLatency>
<IterationLatency>
<range>
<min>3</min>
<max>65541</max>
</range>
</IterationLatency>
<LOOP_HASH_SEARCH2>
<TripCount>
<range>
<min>1</min>
<max>65536</max>
</range>
</TripCount>
<Latency>
<range>
<min>1</min>
<max>65536</max>
</range>
</Latency>
<AbsoluteTimeLatency>
<range>
<min>6</min>
<max>437125</max>
</range>
</AbsoluteTimeLatency>
<PipelineII>1</PipelineII>
<PipelineDepth>2</PipelineDepth>
</LOOP_HASH_SEARCH2>
</LOOP_HASH_SEARCH1>
</SummaryOfLoopLatency>
</PerformanceEstimates>

<AreaEstimates>
<Resources>
<BRAM_18K>0</BRAM_18K>
<FF>665</FF>
<LUT>1331</LUT>
<DSP>0</DSP>
<URAM>0</URAM>
</Resources>
<AvailableResources>
<BRAM_18K>432</BRAM_18K>
<DSP>360</DSP>
<FF>141120</FF>
<LUT>70560</LUT>
<URAM>0</URAM>
</AvailableResources>
</AreaEstimates>

<InterfaceSummary>
<RtlPorts>
<name>ap_clk</name>
<Object>hash_search</Object>
<Type>return value</Type>
<Scope></Scope>
<IOProtocol>ap_ctrl_hs</IOProtocol>
<IOConfig></IOConfig>
<Dir>in</Dir>
<Bits>1</Bits>
<Attribute>control</Attribute>
</RtlPorts>
<RtlPorts>
<name>ap_rst</name>
<Object>hash_search</Object>
<Type>return value</Type>
<Scope></Scope>
<IOProtocol>ap_ctrl_hs</IOProtocol>
<IOConfig></IOConfig>
<Dir>in</Dir>
<Bits>1</Bits>
<Attribute>control</Attribute>
</RtlPorts>
<RtlPorts>
<name>ap_start</name>
<Object>hash_search</Object>
<Type>return value</Type>
<Scope></Scope>
<IOProtocol>ap_ctrl_hs</IOProtocol>
<IOConfig></IOConfig>
<Dir>in</Dir>
<Bits>1</Bits>
<Attribute>control</Attribute>
</RtlPorts>
<RtlPorts>
<name>ap_done</name>
<Object>hash_search</Object>
<Type>return value</Type>
<Scope></Scope>
<IOProtocol>ap_ctrl_hs</IOProtocol>
<IOConfig></IOConfig>
<Dir>out</Dir>
<Bits>1</Bits>
<Attribute>control</Attribute>
</RtlPorts>
<RtlPorts>
<name>ap_idle</name>
<Object>hash_search</Object>
<Type>return value</Type>
<Scope></Scope>
<IOProtocol>ap_ctrl_hs</IOProtocol>
<IOConfig></IOConfig>
<Dir>out</Dir>
<Bits>1</Bits>
<Attribute>control</Attribute>
</RtlPorts>
<RtlPorts>
<name>ap_ready</name>
<Object>hash_search</Object>
<Type>return value</Type>
<Scope></Scope>
<IOProtocol>ap_ctrl_hs</IOProtocol>
<IOConfig></IOConfig>
<Dir>out</Dir>
<Bits>1</Bits>
<Attribute>control</Attribute>
</RtlPorts>
<RtlPorts>
<name>ap_return</name>
<Object>hash_search</Object>
<Type>return value</Type>
<Scope></Scope>
<IOProtocol>ap_ctrl_hs</IOProtocol>
<IOConfig></IOConfig>
<Dir>out</Dir>
<Bits>16</Bits>
<Attribute>data</Attribute>
</RtlPorts>
<RtlPorts>
<name>key_address0</name>
<Object>key</Object>
<Type>array</Type>
<Scope></Scope>
<IOProtocol>ap_memory</IOProtocol>
<IOConfig></IOConfig>
<Dir>out</Dir>
<Bits>13</Bits>
<Attribute>address</Attribute>
</RtlPorts>
<RtlPorts>
<name>key_ce0</name>
<Object>key</Object>
<Type>array</Type>
<Scope></Scope>
<IOProtocol>ap_memory</IOProtocol>
<IOConfig></IOConfig>
<Dir>out</Dir>
<Bits>1</Bits>
<Attribute>control</Attribute>
</RtlPorts>
<RtlPorts>
<name>key_q0</name>
<Object>key</Object>
<Type>array</Type>
<Scope></Scope>
<IOProtocol>ap_memory</IOProtocol>
<IOConfig></IOConfig>
<Dir>in</Dir>
<Bits>8</Bits>
<Attribute>data</Attribute>
</RtlPorts>
<RtlPorts>
<name>key_address1</name>
<Object>key</Object>
<Type>array</Type>
<Scope></Scope>
<IOProtocol>ap_memory</IOProtocol>
<IOConfig></IOConfig>
<Dir>out</Dir>
<Bits>13</Bits>
<Attribute>address</Attribute>
</RtlPorts>
<RtlPorts>
<name>key_ce1</name>
<Object>key</Object>
<Type>array</Type>
<Scope></Scope>
<IOProtocol>ap_memory</IOProtocol>
<IOConfig></IOConfig>
<Dir>out</Dir>
<Bits>1</Bits>
<Attribute>control</Attribute>
</RtlPorts>
<RtlPorts>
<name>key_q1</name>
<Object>key</Object>
<Type>array</Type>
<Scope></Scope>
<IOProtocol>ap_memory</IOProtocol>
<IOConfig></IOConfig>
<Dir>in</Dir>
<Bits>8</Bits>
<Attribute>data</Attribute>
</RtlPorts>
<RtlPorts>
<name>hashArr_location_address0</name>
<Object>hashArr_location</Object>
<Type>array</Type>
<Scope></Scope>
<IOProtocol>ap_memory</IOProtocol>
<IOConfig></IOConfig>
<Dir>out</Dir>
<Bits>18</Bits>
<Attribute>address</Attribute>
</RtlPorts>
<RtlPorts>
<name>hashArr_location_ce0</name>
<Object>hashArr_location</Object>
<Type>array</Type>
<Scope></Scope>
<IOProtocol>ap_memory</IOProtocol>
<IOConfig></IOConfig>
<Dir>out</Dir>
<Bits>1</Bits>
<Attribute>control</Attribute>
</RtlPorts>
<RtlPorts>
<name>hashArr_location_q0</name>
<Object>hashArr_location</Object>
<Type>array</Type>
<Scope></Scope>
<IOProtocol>ap_memory</IOProtocol>
<IOConfig></IOConfig>
<Dir>in</Dir>
<Bits>16</Bits>
<Attribute>data</Attribute>
</RtlPorts>
<RtlPorts>
<name>hashArr_start_address0</name>
<Object>hashArr_start</Object>
<Type>array</Type>
<Scope></Scope>
<IOProtocol>ap_memory</IOProtocol>
<IOConfig></IOConfig>
<Dir>out</Dir>
<Bits>18</Bits>
<Attribute>address</Attribute>
</RtlPorts>
<RtlPorts>
<name>hashArr_start_ce0</name>
<Object>hashArr_start</Object>
<Type>array</Type>
<Scope></Scope>
<IOProtocol>ap_memory</IOProtocol>
<IOConfig></IOConfig>
<Dir>out</Dir>
<Bits>1</Bits>
<Attribute>control</Attribute>
</RtlPorts>
<RtlPorts>
<name>hashArr_start_q0</name>
<Object>hashArr_start</Object>
<Type>array</Type>
<Scope></Scope>
<IOProtocol>ap_memory</IOProtocol>
<IOConfig></IOConfig>
<Dir>in</Dir>
<Bits>16</Bits>
<Attribute>data</Attribute>
</RtlPorts>
<RtlPorts>
<name>hashArr_start_address1</name>
<Object>hashArr_start</Object>
<Type>array</Type>
<Scope></Scope>
<IOProtocol>ap_memory</IOProtocol>
<IOConfig></IOConfig>
<Dir>out</Dir>
<Bits>18</Bits>
<Attribute>address</Attribute>
</RtlPorts>
<RtlPorts>
<name>hashArr_start_ce1</name>
<Object>hashArr_start</Object>
<Type>array</Type>
<Scope></Scope>
<IOProtocol>ap_memory</IOProtocol>
<IOConfig></IOConfig>
<Dir>out</Dir>
<Bits>1</Bits>
<Attribute>control</Attribute>
</RtlPorts>
<RtlPorts>
<name>hashArr_start_q1</name>
<Object>hashArr_start</Object>
<Type>array</Type>
<Scope></Scope>
<IOProtocol>ap_memory</IOProtocol>
<IOConfig></IOConfig>
<Dir>in</Dir>
<Bits>16</Bits>
<Attribute>data</Attribute>
</RtlPorts>
<RtlPorts>
<name>hashArr_empty_flag_address0</name>
<Object>hashArr_empty_flag</Object>
<Type>array</Type>
<Scope></Scope>
<IOProtocol>ap_memory</IOProtocol>
<IOConfig></IOConfig>
<Dir>out</Dir>
<Bits>18</Bits>
<Attribute>address</Attribute>
</RtlPorts>
<RtlPorts>
<name>hashArr_empty_flag_ce0</name>
<Object>hashArr_empty_flag</Object>
<Type>array</Type>
<Scope></Scope>
<IOProtocol>ap_memory</IOProtocol>
<IOConfig></IOConfig>
<Dir>out</Dir>
<Bits>1</Bits>
<Attribute>control</Attribute>
</RtlPorts>
<RtlPorts>
<name>hashArr_empty_flag_q0</name>
<Object>hashArr_empty_flag</Object>
<Type>array</Type>
<Scope></Scope>
<IOProtocol>ap_memory</IOProtocol>
<IOConfig></IOConfig>
<Dir>in</Dir>
<Bits>1</Bits>
<Attribute>data</Attribute>
</RtlPorts>
<RtlPorts>
<name>hashArr_empty_flag_address1</name>
<Object>hashArr_empty_flag</Object>
<Type>array</Type>
<Scope></Scope>
<IOProtocol>ap_memory</IOProtocol>
<IOConfig></IOConfig>
<Dir>out</Dir>
<Bits>18</Bits>
<Attribute>address</Attribute>
</RtlPorts>
<RtlPorts>
<name>hashArr_empty_flag_ce1</name>
<Object>hashArr_empty_flag</Object>
<Type>array</Type>
<Scope></Scope>
<IOProtocol>ap_memory</IOProtocol>
<IOConfig></IOConfig>
<Dir>out</Dir>
<Bits>1</Bits>
<Attribute>control</Attribute>
</RtlPorts>
<RtlPorts>
<name>hashArr_empty_flag_q1</name>
<Object>hashArr_empty_flag</Object>
<Type>array</Type>
<Scope></Scope>
<IOProtocol>ap_memory</IOProtocol>
<IOConfig></IOConfig>
<Dir>in</Dir>
<Bits>1</Bits>
<Attribute>data</Attribute>
</RtlPorts>
<RtlPorts>
<name>key_offset</name>
<Object>key_offset</Object>
<Type>scalar</Type>
<Scope></Scope>
<IOProtocol>ap_none</IOProtocol>
<IOConfig></IOConfig>
<Dir>in</Dir>
<Bits>13</Bits>
<Attribute>data</Attribute>
</RtlPorts>
<RtlPorts>
<name>hash</name>
<Object>hash</Object>
<Type>scalar</Type>
<Scope></Scope>
<IOProtocol>ap_none</IOProtocol>
<IOConfig></IOConfig>
<Dir>in</Dir>
<Bits>14</Bits>
<Attribute>data</Attribute>
</RtlPorts>
<RtlPorts>
<name>len</name>
<Object>len</Object>
<Type>scalar</Type>
<Scope></Scope>
<IOProtocol>ap_none</IOProtocol>
<IOConfig></IOConfig>
<Dir>in</Dir>
<Bits>18</Bits>
<Attribute>data</Attribute>
</RtlPorts>
</InterfaceSummary>

</profile>
